underautomation/__init__.py
underautomation/universal_robots/__init__.py
underautomation/universal_robots/connect_parameters.py
underautomation/universal_robots/ur.py
underautomation/universal_robots/common/__init__.py
underautomation/universal_robots/common/analog_ranges.py
underautomation/universal_robots/common/cartesian_coordinates.py
underautomation/universal_robots/common/control_modes.py
underautomation/universal_robots/common/controller_box_types.py
underautomation/universal_robots/common/dashboard_connect_parameters.py
underautomation/universal_robots/common/digital_output_configurations.py
underautomation/universal_robots/common/global_variable.py
underautomation/universal_robots/common/global_variable_types.py
underautomation/universal_robots/common/global_variable_value.py
underautomation/universal_robots/common/i_ur_dh_parameters.py
underautomation/universal_robots/common/internal_error_event_args.py
underautomation/universal_robots/common/interpreter_mode_connect_parameters.py
underautomation/universal_robots/common/joint_modes.py
underautomation/universal_robots/common/joints_double_values.py
underautomation/universal_robots/common/joints_int_values.py
underautomation/universal_robots/common/joints_values_1.py
underautomation/universal_robots/common/output_modes.py
underautomation/universal_robots/common/package_event_args.py
underautomation/universal_robots/common/pose.py
underautomation/universal_robots/common/primary_interface_connect_parameters.py
underautomation/universal_robots/common/robot_models.py
underautomation/universal_robots/common/robot_models_extended.py
underautomation/universal_robots/common/robot_modes.py
underautomation/universal_robots/common/robot_sub_types.py
underautomation/universal_robots/common/rtde_connect_parameters.py
underautomation/universal_robots/common/safety_status.py
underautomation/universal_robots/common/socket_communication_connect_parameters.py
underautomation/universal_robots/common/ssh_connect_parameters.py
underautomation_universalrobots-8.2.0.0.dist-info/METADATA
underautomation_universalrobots-8.2.0.0.dist-info/WHEEL
underautomation_universalrobots-8.2.0.0.dist-info/top_level.txt
underautomation_universalrobots-8.2.0.0.dist-info/RECORD
