Metadata-Version: 2.4
Name: UnderAutomation.UniversalRobots
Version: 8.2.0.0
Summary: Quickly create applications that communicate with your Universal Robots cobot
Home-page: https://underautomation.com/universal-robots
Author: UnderAutomation
Author-email: support@underautomation.com
Project-URL: Documentation, https://underautomation.com/universal-robots/documentation/get-started-python
Project-URL: Source, https://github.com/underautomation/UniversalRobots.py
Requires-Python: >=3.7
Requires-Dist: pythonnet==3.0.5
Dynamic: author
Dynamic: author-email
Dynamic: description
Dynamic: description-content-type
Dynamic: home-page
Dynamic: project-url
Dynamic: requires-dist
Dynamic: requires-python
Dynamic: summary
